README.md
setup.py
farhad_distributions/Binomialdistribution.py
farhad_distributions/Gaussiandistribution.py
farhad_distributions/Generaldistribution.py
farhad_distributions/__init__.py
farhad_distributions.egg-info/PKG-INFO
farhad_distributions.egg-info/SOURCES.txt
farhad_distributions.egg-info/dependency_links.txt
farhad_distributions.egg-info/not-zip-safe
farhad_distributions.egg-info/top_level.txt