Metadata-Version: 1.0
Name: farhad-distributions
Version: 0.1
Summary: Gaussian distributions
Home-page: UNKNOWN
Author: Farhad Kamal
Author-email: jitubd1971@gmail.com
License: UNKNOWN
Platform: UNKNOWN
